{
	"info": {
		"_postman_id": "f974f4ba-4455-40e2-abc4-96a3e364d395",
		"name": "Api Musicas2",
		"schema": "https://schema.getpostman.com/json/collection/v2.1.0/collection.json"
	},
	"item": [
		{
			"name": "Albums",
			"item": [
				{
					"name": "Count Albums",
					"request": {
						"method": "GET",
						"header": [
							{
								"key": "accept",
								"value": "application/json"
							}
						],
						"url": {
							"raw": "http://[::1]:3000/albums/count",
							"protocol": "http",
							"host": [
								"[::1]"
							],
							"port": "3000",
							"path": [
								"albums",
								"count"
							]
						}
					},
					"response": []
				},
				{
					"name": "Delete Album",
					"request": {
						"method": "DELETE",
						"header": [
							{
								"key": "accept",
								"value": "application/json"
							}
						],
						"url": {
							"raw": "http://[::1]:3000/albums/2",
							"protocol": "http",
							"host": [
								"[::1]"
							],
							"port": "3000",
							"path": [
								"albums",
								"2"
							]
						}
					},
					"response": []
				},
				{
					"name": "Show Album",
					"request": {
						"method": "GET",
						"header": [
							{
								"key": "accept",
								"value": "application/json"
							}
						],
						"url": {
							"raw": "http://[::1]:3000/albums/5",
							"protocol": "http",
							"host": [
								"[::1]"
							],
							"port": "3000",
							"path": [
								"albums",
								"5"
							]
						}
					},
					"response": []
				},
				{
					"name": "Create Album",
					"request": {
						"method": "POST",
						"header": [
							{
								"key": "accept",
								"value": "application/json"
							},
							{
								"key": "Content-Type",
								"value": "application/json"
							}
						],
						"body": {
							"mode": "raw",
							"raw": "{\n  \"nomealbum\": \"teste\"\n}"
						},
						"url": {
							"raw": "http://[::1]:3000/albums",
							"protocol": "http",
							"host": [
								"[::1]"
							],
							"port": "3000",
							"path": [
								"albums"
							]
						}
					},
					"response": []
				},
				{
					"name": "Show All Albums",
					"request": {
						"method": "GET",
						"header": [
							{
								"key": "accept",
								"value": "application/json"
							}
						],
						"url": {
							"raw": "http://[::1]:3000/albums",
							"protocol": "http",
							"host": [
								"[::1]"
							],
							"port": "3000",
							"path": [
								"albums"
							]
						}
					},
					"response": []
				},
				{
					"name": "Change Album",
					"request": {
						"method": "PUT",
						"header": [
							{
								"key": "accept",
								"value": "application/json"
							},
							{
								"key": "Content-Type",
								"value": "application/json"
							}
						],
						"body": {
							"mode": "raw",
							"raw": "{\n  \"id\": 3,\n  \"nomealbum\": \"string\"\n}"
						},
						"url": {
							"raw": "http://[::1]:3000/albums/3",
							"protocol": "http",
							"host": [
								"[::1]"
							],
							"port": "3000",
							"path": [
								"albums",
								"3"
							]
						}
					},
					"response": []
				},
				{
					"name": "Change Album",
					"request": {
						"method": "PATCH",
						"header": [
							{
								"key": "accept",
								"value": "application/json"
							},
							{
								"key": "Content-Type",
								"value": "application/json"
							}
						],
						"body": {
							"mode": "raw",
							"raw": "{\n  \"id\": 4,\n  \"nomealbum\": \"string\"\n}"
						},
						"url": {
							"raw": "http://[::1]:3000/albums/4",
							"protocol": "http",
							"host": [
								"[::1]"
							],
							"port": "3000",
							"path": [
								"albums",
								"4"
							]
						}
					},
					"response": []
				},
				{
					"name": "Change All Albums",
					"request": {
						"method": "PATCH",
						"header": [
							{
								"key": "accept",
								"value": "application/json"
							},
							{
								"key": "Content-Type",
								"value": "application/json"
							}
						],
						"body": {
							"mode": "raw",
							"raw": "{\n  \"id\": 1,\n  \"nomealbum\": \"string\"\n}"
						},
						"url": {
							"raw": "http://[::1]:3000/albums",
							"protocol": "http",
							"host": [
								"[::1]"
							],
							"port": "3000",
							"path": [
								"albums"
							]
						}
					},
					"response": []
				}
			]
		},
		{
			"name": "AlbumsMusica",
			"item": [
				{
					"name": "Show Musics Album (mostrar musicas que pretencem ao album)",
					"request": {
						"method": "GET",
						"header": [
							{
								"key": "accept",
								"value": "application/json"
							}
						],
						"url": {
							"raw": "http://[::1]:3000/albums/20/musicas",
							"protocol": "http",
							"host": [
								"[::1]"
							],
							"port": "3000",
							"path": [
								"albums",
								"20",
								"musicas"
							]
						}
					},
					"response": []
				},
				{
					"name": "Delete Albums (eliminar Albums)",
					"request": {
						"method": "DELETE",
						"header": [
							{
								"key": "accept",
								"value": "application/json"
							}
						],
						"url": {
							"raw": "http://[::1]:3000/albums/3/musicas",
							"protocol": "http",
							"host": [
								"[::1]"
							],
							"port": "3000",
							"path": [
								"albums",
								"3",
								"musicas"
							]
						}
					},
					"response": []
				}
			]
		},
		{
			"name": "Artists",
			"item": [
				{
					"name": "Count Artists",
					"request": {
						"method": "GET",
						"header": [
							{
								"key": "accept",
								"value": "application/json"
							}
						],
						"url": {
							"raw": "http://[::1]:3000/artistas/count",
							"protocol": "http",
							"host": [
								"[::1]"
							],
							"port": "3000",
							"path": [
								"artistas",
								"count"
							]
						}
					},
					"response": []
				},
				{
					"name": "Show Artist",
					"request": {
						"method": "GET",
						"header": [
							{
								"key": "accept",
								"value": "application/json"
							}
						],
						"url": {
							"raw": "http://[::1]:3000/artistas/1",
							"protocol": "http",
							"host": [
								"[::1]"
							],
							"port": "3000",
							"path": [
								"artistas",
								"1"
							]
						}
					},
					"response": []
				},
				{
					"name": "Delete Artist",
					"request": {
						"method": "DELETE",
						"header": [
							{
								"key": "accept",
								"value": "application/json"
							}
						],
						"url": {
							"raw": "http://[::1]:3000/artistas/4",
							"protocol": "http",
							"host": [
								"[::1]"
							],
							"port": "3000",
							"path": [
								"artistas",
								"4"
							]
						}
					},
					"response": []
				},
				{
					"name": "Show All Artists",
					"request": {
						"method": "GET",
						"header": [
							{
								"key": "accept",
								"value": "application/json"
							}
						],
						"url": {
							"raw": "http://[::1]:3000/artistas",
							"protocol": "http",
							"host": [
								"[::1]"
							],
							"port": "3000",
							"path": [
								"artistas"
							]
						}
					},
					"response": []
				},
				{
					"name": "Create Artist",
					"request": {
						"method": "POST",
						"header": [
							{
								"key": "accept",
								"value": "application/json"
							},
							{
								"key": "Content-Type",
								"value": "application/json"
							}
						],
						"body": {
							"mode": "raw",
							"raw": "{\n  \"nomeartista\": \"string\",\n  \"pais\": \"string\"\n}"
						},
						"url": {
							"raw": "http://[::1]:3000/artistas",
							"protocol": "http",
							"host": [
								"[::1]"
							],
							"port": "3000",
							"path": [
								"artistas"
							]
						}
					},
					"response": []
				},
				{
					"name": "Change Artist",
					"request": {
						"method": "PUT",
						"header": [
							{
								"key": "accept",
								"value": "application/json"
							},
							{
								"key": "Content-Type",
								"value": "application/json"
							}
						],
						"body": {
							"mode": "raw",
							"raw": "{\n  \"id\": 1,\n  \"nomeartista\": \"string\",\n  \"pais\": \"string\"\n}"
						},
						"url": {
							"raw": "http://[::1]:3000/artistas/1",
							"protocol": "http",
							"host": [
								"[::1]"
							],
							"port": "3000",
							"path": [
								"artistas",
								"1"
							]
						}
					},
					"response": []
				},
				{
					"name": "Change Artists",
					"request": {
						"method": "PATCH",
						"header": [
							{
								"key": "accept",
								"value": "application/json"
							},
							{
								"key": "Content-Type",
								"value": "application/json"
							}
						],
						"body": {
							"mode": "raw",
							"raw": "{\n  \"id\": 2,\n  \"nomeartista\": \"string\",\n  \"pais\": \"string\"\n}"
						},
						"url": {
							"raw": "http://[::1]:3000/artistas/2",
							"protocol": "http",
							"host": [
								"[::1]"
							],
							"port": "3000",
							"path": [
								"artistas",
								"2"
							]
						}
					},
					"response": []
				},
				{
					"name": "Change All Artists",
					"request": {
						"method": "PATCH",
						"header": [
							{
								"key": "accept",
								"value": "application/json"
							},
							{
								"key": "Content-Type",
								"value": "application/json"
							}
						],
						"body": {
							"mode": "raw",
							"raw": "{\n  \"id\": 0,\n  \"nomeartista\": \"string\",\n  \"pais\": \"string\"\n}"
						},
						"url": {
							"raw": "http://[::1]:3000/artistas",
							"protocol": "http",
							"host": [
								"[::1]"
							],
							"port": "3000",
							"path": [
								"artistas"
							]
						}
					},
					"response": []
				}
			]
		},
		{
			"name": "Musics",
			"item": [
				{
					"name": "Musics Count",
					"request": {
						"method": "GET",
						"header": [
							{
								"key": "accept",
								"value": "application/json"
							}
						],
						"url": {
							"raw": "http://[::1]:3000/musicas/count",
							"protocol": "http",
							"host": [
								"[::1]"
							],
							"port": "3000",
							"path": [
								"musicas",
								"count"
							]
						}
					},
					"response": []
				},
				{
					"name": "Show Music",
					"request": {
						"method": "GET",
						"header": [
							{
								"key": "accept",
								"value": "application/json"
							}
						],
						"url": {
							"raw": "http://[::1]:3000/musicas/6",
							"protocol": "http",
							"host": [
								"[::1]"
							],
							"port": "3000",
							"path": [
								"musicas",
								"6"
							]
						}
					},
					"response": []
				},
				{
					"name": "Delete Music",
					"request": {
						"method": "DELETE",
						"header": [
							{
								"key": "accept",
								"value": "application/json"
							}
						],
						"url": {
							"raw": "http://[::1]:3000/musicas/5",
							"protocol": "http",
							"host": [
								"[::1]"
							],
							"port": "3000",
							"path": [
								"musicas",
								"5"
							]
						}
					},
					"response": []
				},
				{
					"name": "Create Music",
					"request": {
						"method": "POST",
						"header": [
							{
								"key": "accept",
								"value": "application/json"
							},
							{
								"key": "Content-Type",
								"value": "application/json"
							}
						],
						"body": {
							"mode": "raw",
							"raw": "{\n  \"nomeMusica\": \"string\",\n  \"genero\": \"string\",\n  \"datadelancamento\": 1,\n  \"nomeartista\": 1,\n  \"albumId\": 1\n}"
						},
						"url": {
							"raw": "http://[::1]:3000/musicas",
							"protocol": "http",
							"host": [
								"[::1]"
							],
							"port": "3000",
							"path": [
								"musicas"
							]
						}
					},
					"response": []
				},
				{
					"name": "Show All Music",
					"request": {
						"method": "GET",
						"header": [
							{
								"key": "accept",
								"value": "application/json"
							}
						],
						"url": {
							"raw": "http://[::1]:3000/musicas",
							"protocol": "http",
							"host": [
								"[::1]"
							],
							"port": "3000",
							"path": [
								"musicas"
							]
						}
					},
					"response": []
				},
				{
					"name": "Change Music",
					"request": {
						"method": "PUT",
						"header": [
							{
								"key": "accept",
								"value": "application/json"
							},
							{
								"key": "Content-Type",
								"value": "application/json"
							}
						],
						"body": {
							"mode": "raw",
							"raw": "{\n  \"id\": 2,\n  \"nomeMusica\": \"string\",\n  \"genero\": \"string\",\n  \"datadelancamento\": 0,\n  \"nomeartista\": 0,\n  \"albumId\": 0\n}"
						},
						"url": {
							"raw": "http://[::1]:3000/musicas/2",
							"protocol": "http",
							"host": [
								"[::1]"
							],
							"port": "3000",
							"path": [
								"musicas",
								"2"
							]
						}
					},
					"response": []
				},
				{
					"name": "Change Music",
					"request": {
						"method": "PATCH",
						"header": [
							{
								"key": "accept",
								"value": "application/json"
							},
							{
								"key": "Content-Type",
								"value": "application/json"
							}
						],
						"body": {
							"mode": "raw",
							"raw": "{\n  \"id\": 3,\n  \"nomeMusica\": \"string\",\n  \"genero\": \"string\",\n  \"datadelancamento\": 0,\n  \"nomeartista\": 0,\n  \"albumId\": 0\n}"
						},
						"url": {
							"raw": "http://[::1]:3000/musicas/3",
							"protocol": "http",
							"host": [
								"[::1]"
							],
							"port": "3000",
							"path": [
								"musicas",
								"3"
							]
						}
					},
					"response": []
				},
				{
					"name": "Change All Musics",
					"request": {
						"method": "PATCH",
						"header": [
							{
								"key": "accept",
								"value": "application/json"
							},
							{
								"key": "Content-Type",
								"value": "application/json"
							}
						],
						"body": {
							"mode": "raw",
							"raw": "{\n  \"id\": 0,\n  \"nomeMusica\": \"string\",\n  \"genero\": \"string\",\n  \"datadelancamento\": 0,\n  \"nomeartista\": 0,\n  \"albumId\": 0\n}"
						},
						"url": {
							"raw": "http://[::1]:3000/musicas",
							"protocol": "http",
							"host": [
								"[::1]"
							],
							"port": "3000",
							"path": [
								"musicas"
							]
						}
					},
					"response": []
				}
			]
		},
		{
			"name": "MusicAlbum",
			"item": [
				{
					"name": "Show Music Album (mostrar a qual album a musica pretence)",
					"request": {
						"method": "GET",
						"header": [
							{
								"key": "accept",
								"value": "application/json"
							}
						],
						"url": {
							"raw": "http://[::1]:3000/musicas/3/album",
							"protocol": "http",
							"host": [
								"[::1]"
							],
							"port": "3000",
							"path": [
								"musicas",
								"3",
								"album"
							]
						}
					},
					"response": []
				}
			]
		},
		{
			"name": "MusicArtist",
			"item": [
				{
					"name": "Show Music Artist (mostrar artista da musica)",
					"request": {
						"method": "GET",
						"header": [
							{
								"key": "accept",
								"value": "application/json"
							}
						],
						"url": {
							"raw": "http://[::1]:3000/musicas/2/artista",
							"protocol": "http",
							"host": [
								"[::1]"
							],
							"port": "3000",
							"path": [
								"musicas",
								"2",
								"artista"
							]
						}
					},
					"response": []
				}
			]
		},
		{
			"name": "Users",
			"item": [
				{
					"name": "Count Users",
					"request": {
						"method": "GET",
						"header": [
							{
								"key": "accept",
								"value": "application/json"
							}
						],
						"url": {
							"raw": "http://[::1]:3000/users/count",
							"protocol": "http",
							"host": [
								"[::1]"
							],
							"port": "3000",
							"path": [
								"users",
								"count"
							]
						}
					},
					"response": []
				},
				{
					"name": "Change User",
					"request": {
						"method": "PUT",
						"header": [
							{
								"key": "accept",
								"value": "application/json"
							},
							{
								"key": "Content-Type",
								"value": "application/json"
							}
						],
						"body": {
							"mode": "raw",
							"raw": "{\n  \"id\": 25,\n  \"nome\": \"string\",\n  \"pais\": \"string\",\n  \"idade\": 0,\n  \"email\": \"string\",\n  \"musicamaisouvida\": 0\n}"
						},
						"url": {
							"raw": "http://[::1]:3000/users/25",
							"protocol": "http",
							"host": [
								"[::1]"
							],
							"port": "3000",
							"path": [
								"users",
								"25"
							]
						}
					},
					"response": []
				},
				{
					"name": "Change User",
					"request": {
						"method": "PATCH",
						"header": [
							{
								"key": "accept",
								"value": "application/json"
							},
							{
								"key": "Content-Type",
								"value": "application/json"
							}
						],
						"body": {
							"mode": "raw",
							"raw": "{\n  \"id\": 26,\n  \"nome\": \"string\",\n  \"pais\": \"string\",\n  \"idade\": 0,\n  \"email\": \"string\",\n  \"musicamaisouvida\": 0\n}"
						},
						"url": {
							"raw": "http://[::1]:3000/users/26",
							"protocol": "http",
							"host": [
								"[::1]"
							],
							"port": "3000",
							"path": [
								"users",
								"26"
							]
						}
					},
					"response": []
				},
				{
					"name": "Show User",
					"request": {
						"method": "GET",
						"header": [
							{
								"key": "accept",
								"value": "application/json"
							}
						],
						"url": {
							"raw": "http://[::1]:3000/users/5",
							"protocol": "http",
							"host": [
								"[::1]"
							],
							"port": "3000",
							"path": [
								"users",
								"5"
							]
						}
					},
					"response": []
				},
				{
					"name": "Create user",
					"request": {
						"method": "POST",
						"header": [
							{
								"key": "accept",
								"value": "application/json"
							},
							{
								"key": "Content-Type",
								"value": "application/json"
							}
						],
						"body": {
							"mode": "raw",
							"raw": "{\n  \"nome\": \"string\",\n  \"pais\": \"string\",\n  \"idade\": 0,\n  \"email\": \"string\",\n  \"musicamaisouvida\": 0\n}"
						},
						"url": {
							"raw": "http://[::1]:3000/users",
							"protocol": "http",
							"host": [
								"[::1]"
							],
							"port": "3000",
							"path": [
								"users"
							]
						}
					},
					"response": []
				},
				{
					"name": "Delete User",
					"request": {
						"method": "DELETE",
						"header": [
							{
								"key": "accept",
								"value": "application/json"
							}
						],
						"url": {
							"raw": "http://[::1]:3000/users/2",
							"protocol": "http",
							"host": [
								"[::1]"
							],
							"port": "3000",
							"path": [
								"users",
								"2"
							]
						}
					},
					"response": []
				},
				{
					"name": "Change All Users",
					"request": {
						"method": "PATCH",
						"header": [
							{
								"key": "accept",
								"value": "application/json"
							},
							{
								"key": "Content-Type",
								"value": "application/json"
							}
						],
						"body": {
							"mode": "raw",
							"raw": "{\n  \"id\": 0,\n  \"nome\": \"string\",\n  \"pais\": \"string\",\n  \"idade\": 0,\n  \"email\": \"string\",\n  \"musicamaisouvida\": 0\n}"
						},
						"url": {
							"raw": "http://[::1]:3000/users",
							"protocol": "http",
							"host": [
								"[::1]"
							],
							"port": "3000",
							"path": [
								"users"
							]
						}
					},
					"response": []
				},
				{
					"name": "Show All Users",
					"request": {
						"method": "GET",
						"header": [
							{
								"key": "accept",
								"value": "application/json"
							}
						],
						"url": {
							"raw": "http://[::1]:3000/users",
							"protocol": "http",
							"host": [
								"[::1]"
							],
							"port": "3000",
							"path": [
								"users"
							]
						}
					},
					"response": []
				}
			]
		},
		{
			"name": "UserMusic",
			"item": [
				{
					"name": "Show User Music(musica mais ouvida de um utilizador)",
					"request": {
						"method": "GET",
						"header": [
							{
								"key": "accept",
								"value": "application/json"
							}
						],
						"url": {
							"raw": "http://[::1]:3000/users/33/musica",
							"protocol": "http",
							"host": [
								"[::1]"
							],
							"port": "3000",
							"path": [
								"users",
								"33",
								"musica"
							]
						}
					},
					"response": []
				}
			]
		}
	]
}